file_organza/__init__.py
file_organza/cli.py
file_organza/organizer.py
file_organza-1.1.4.dist-info/METADATA
file_organza-1.1.4.dist-info/WHEEL
file_organza-1.1.4.dist-info/entry_points.txt
file_organza-1.1.4.dist-info/top_level.txt
file_organza-1.1.4.dist-info/RECORD
