Metadata-Version: 2.1
Name: file_organza
Version: 1.1.4
Summary: A Python package to organize files by type or date
Home-page: https://github.com/asimsolehria/file_organza
Author: Your Name
Author-email: your.email@example.com
Classifier: Programming Language :: Python :: 3
Classifier: License :: OSI Approved :: MIT License
Classifier: Operating System :: OS Independent
Requires-Python: >=3.6
Requires-Dist: pytest>=6.0
